heliopy_multid/__init__.py
heliopy_multid/data/__init__.py
heliopy_multid/data/cluster.py
heliopy_multid/data/mms.py
heliopy_multid/data/util.py
heliopy_multid/data/test/__init__.py
heliopy_multid/data/test/test_cluster.py
heliopy_multid/data/test/test_mms.py
heliopy_multid/data/test/util.py
heliopy_multid-0.0.3.dist-info/LICENSE
heliopy_multid-0.0.3.dist-info/METADATA
heliopy_multid-0.0.3.dist-info/WHEEL
heliopy_multid-0.0.3.dist-info/top_level.txt
heliopy_multid-0.0.3.dist-info/RECORD
