Metadata-Version: 2.1
Name: heliopy-multid
Version: 0.0.3
Summary: Extension to heliopy to retrieve multi-dimensional heliopheric data
Home-page: https://gitlab.com/aidaspace/heliopy_multid
Author: AIDA Consortium
Author-email: coordinator.aida@kuleuven.be
License: GNU GPLv3
Platform: UNKNOWN
Requires-Python: >=3.5
Requires-Dist: numpy
Requires-Dist: pandas
Requires-Dist: xarray
Requires-Dist: astropy
Requires-Dist: heliopy
Requires-Dist: sunpy
Requires-Dist: cdflib
Requires-Dist: requests
Requires-Dist: wget
